svgd/__init__.py
svgd/sampler.py
svgd/states.py
svgd/callbacks/__init__.py
svgd/callbacks/breaker.py
svgd/callbacks/callback.py
svgd/callbacks/detacher.py
svgd/callbacks/logger.py
svgd/distributions/__init__.py
svgd/distributions/distribution.py
svgd/distributions/gaussian.py
svgd/distributions/gmm.py
svgd/distributions/torch.py
svgd/kernels/__init__.py
svgd/kernels/imq.py
svgd/kernels/kernel.py
svgd/kernels/rbf.py
svgd/kernels/rbfd.py
svgd/kernels/rbfw.py
svgd/kernels/parameters/__init__.py
svgd/kernels/parameters/gnn.py
svgd/kernels/parameters/heuristic.py
svgd/kernels/parameters/kp.py
svgd/kernels/parameters/parameter.py
svgd/kernels/parameters/step_parameter.py
svgd/lrs/__init__.py
svgd/lrs/lr.py
svgd/lrs/parameter.py
svgd/lrs/step.py
svgd/lrs/step_parameter.py
svgd-1.0.5.dist-info/METADATA
svgd-1.0.5.dist-info/WHEEL
svgd-1.0.5.dist-info/licenses/LICENSE
svgd-1.0.5.dist-info/RECORD
